urbansim/__init__.py
urbansim/accounts.py
urbansim/exceptions.py
urbansim/developer/__init__.py
urbansim/developer/developer.py
urbansim/developer/sqftproforma.py
urbansim/maps/__init__.py
urbansim/maps/dframe_explorer.html
urbansim/maps/dframe_explorer.py
urbansim/models/__init__.py
urbansim/models/dcm.py
urbansim/models/regression.py
urbansim/models/relocation.py
urbansim/models/supplydemand.py
urbansim/models/transition.py
urbansim/models/util.py
urbansim/urbanchoice/__init__.py
urbansim/urbanchoice/interaction.py
urbansim/urbanchoice/mnl.py
urbansim/urbanchoice/pmat.py
urbansim/utils/__init__.py
urbansim/utils/logutil.py
urbansim/utils/misc.py
urbansim/utils/networks.py
urbansim/utils/sampling.py
urbansim/utils/testing.py
urbansim/utils/yamlio.py
urbansim-3.2.dist-info/LICENSE.txt
urbansim-3.2.dist-info/METADATA
urbansim-3.2.dist-info/WHEEL
urbansim-3.2.dist-info/top_level.txt
urbansim-3.2.dist-info/RECORD
