Metadata-Version: 2.1
Name: urbansim
Version: 3.2
Summary: Platform for building statistical models of cities and regions
Home-page: https://github.com/udst/urbansim
Author: UrbanSim Inc.
Author-email: info@urbansim.com
License: BSD
Platform: UNKNOWN
Classifier: Intended Audience :: Science/Research
Classifier: Topic :: Scientific/Engineering :: Information Analysis
Classifier: Programming Language :: Python :: 2
Classifier: Programming Language :: Python :: 2.7
Classifier: Programming Language :: Python :: 3
Classifier: Programming Language :: Python :: 3.5
Classifier: Programming Language :: Python :: 3.6
Classifier: Programming Language :: Python :: 3.7
Classifier: Programming Language :: Python :: 3.8
Classifier: License :: OSI Approved :: BSD License
Requires-Dist: numpy (>=1.8.0)
Requires-Dist: orca (>=1.1)
Requires-Dist: pandas (>=0.17.0)
Requires-Dist: patsy (>=0.4.1)
Requires-Dist: prettytable (>=0.7.2)
Requires-Dist: pyyaml (>=3.10)
Requires-Dist: scipy (>=1.0)
Requires-Dist: toolz (>=0.8.1)
Requires-Dist: statsmodels (<0.11,>=0.8) ; python_version < "3.6"
Requires-Dist: statsmodels (>=0.8) ; python_version >= "3.6"
